setup.py
ethereum_trie.egg-info/PKG-INFO
ethereum_trie.egg-info/SOURCES.txt
ethereum_trie.egg-info/dependency_links.txt
ethereum_trie.egg-info/not-zip-safe
ethereum_trie.egg-info/requires.txt
ethereum_trie.egg-info/top_level.txt
trie/__init__.py
trie/constants.py
trie/exceptions.py
trie/trie.py
trie/validation.py
trie/db/__init__.py
trie/db/base.py
trie/db/memory.py
trie/utils/__init__.py
trie/utils/nibbles.py
trie/utils/nodes.py
trie/utils/sha3.py